jet_pytorch/__init__.py
jet_pytorch/jet.py
jet_pytorch/sample.py
jet_pytorch/train.py
jet_pytorch/util.py
jet_pytorch-0.0.2.dist-info/LICENSE
jet_pytorch-0.0.2.dist-info/METADATA
jet_pytorch-0.0.2.dist-info/WHEEL
jet_pytorch-0.0.2.dist-info/top_level.txt
jet_pytorch-0.0.2.dist-info/RECORD
