Metadata-Version: 2.2
Name: jet-pytorch
Version: 0.0.2
Summary: A Pytorch port of the code from "Jet: A Modern Transformer-Based Normalizing Flow"
Home-page: https://github.com/btrude/jet-pytorch
Author: Brandon Trude
Author-email: brandon.trude@gmail.com
License: Apache 2.0 License
License-File: LICENSE
Requires-Dist: einops
Requires-Dist: fire
Requires-Dist: huggingface_hub
Requires-Dist: matplotlib
Requires-Dist: numpy
Requires-Dist: opt-einsum
Requires-Dist: safetensors
Requires-Dist: torch
Requires-Dist: torchvision
Requires-Dist: tqdm
Dynamic: author
Dynamic: author-email
Dynamic: description
Dynamic: description-content-type
Dynamic: home-page
Dynamic: license
Dynamic: requires-dist
Dynamic: summary
